timecount/__init__.py
timecount/lib.py
timecount/tctypes.py
timecount-0.3.0.dist-info/METADATA
timecount-0.3.0.dist-info/WHEEL
timecount-0.3.0.dist-info/entry_points.txt
timecount-0.3.0.dist-info/top_level.txt
timecount-0.3.0.dist-info/RECORD
