Metadata-Version: 2.1
Name: timecount
Version: 0.3.0
Summary: UNKNOWN
Home-page: https://github.com/feluxe/timecount
Author: Felix Meyer-Wolters
Author-email: felix@meyerwolters.de
Maintainer: Felix Meyer-Wolters
Maintainer-email: felix@meyerwolters.de
License: Apache 2.0
Download-URL: https://github.com/feluxe/timecount/tarball/0.3.0
Keywords: time,count
Platform: 
